odoo/addons/role_policy_sale/README.rst
odoo/addons/role_policy_sale/__init__.py
odoo/addons/role_policy_sale/__manifest__.py
odoo/addons/role_policy_sale/i18n/role_policy_sale.pot
odoo/addons/role_policy_sale/models/__init__.py
odoo/addons/role_policy_sale/models/product_product.py
odoo/addons/role_policy_sale/readme/CONFIGURE.rst
odoo/addons/role_policy_sale/readme/CONTRIBUTORS.rst
odoo/addons/role_policy_sale/readme/DESCRIPTION.rst
odoo/addons/role_policy_sale/static/description/icon.png
odoo/addons/role_policy_sale/static/description/index.html
odoo13_addon_role_policy_sale-13.0.1.0.1.dev16.dist-info/METADATA
odoo13_addon_role_policy_sale-13.0.1.0.1.dev16.dist-info/WHEEL
odoo13_addon_role_policy_sale-13.0.1.0.1.dev16.dist-info/top_level.txt
odoo13_addon_role_policy_sale-13.0.1.0.1.dev16.dist-info/RECORD
